claude_setup/__init__.py
claude_setup/__main__.py
claude_setup/cli.py
claude_setup/config.py
claude_setup/scaffolder.py
claude_setup/agents/__init__.py
claude_setup/agents/generator.py
claude_setup/templates/__init__.py
claude_setup/templates/manager.py
claude_setup/templates/builtin/api/settings.json
claude_setup/templates/builtin/api/agents/api-architect.md
claude_setup/templates/builtin/api/agents/database-expert.md
claude_setup/templates/builtin/api/commands/endpoint.md
claude_setup/templates/builtin/api/commands/migration.md
claude_setup/templates/builtin/api/commands/seed.md
claude_setup/templates/builtin/api/commands/test.md
claude_setup/templates/builtin/cli/settings.json
claude_setup/templates/builtin/cli/agents/cli-expert.md
claude_setup/templates/builtin/cli/commands/build.md
claude_setup/templates/builtin/cli/commands/command.md
claude_setup/templates/builtin/cli/commands/release.md
claude_setup/templates/builtin/data-science/settings.json
claude_setup/templates/builtin/data-science/agents/data-scientist.md
claude_setup/templates/builtin/data-science/agents/ml-engineer.md
claude_setup/templates/builtin/data-science/commands/evaluate.md
claude_setup/templates/builtin/data-science/commands/explore.md
claude_setup/templates/builtin/data-science/commands/train.md
claude_setup/templates/builtin/generic/settings.json
claude_setup/templates/builtin/generic/agents/scaffolder.md
claude_setup/templates/builtin/generic/commands/help.md
claude_setup/templates/builtin/web/settings.json
claude_setup/templates/builtin/web/agents/performance-optimizer.md
claude_setup/templates/builtin/web/agents/ui-designer.md
claude_setup/templates/builtin/web/commands/a11y.md
claude_setup/templates/builtin/web/commands/build.md
claude_setup/templates/builtin/web/commands/component.md
claude_setup/templates/builtin/web/commands/test.md
claude_setup/utils/__init__.py
claude_setup/utils/detector.py
claude_setup/utils/validator.py
claude_setup-1.0.0.dist-info/METADATA
claude_setup-1.0.0.dist-info/WHEEL
claude_setup-1.0.0.dist-info/entry_points.txt
claude_setup-1.0.0.dist-info/licenses/LICENSE
claude_setup-1.0.0.dist-info/RECORD
