Metadata-Version: 2.4
Name: claude-setup
Version: 1.0.0
Summary: Intelligent scaffolding system for Claude Code configurations - Generate optimal .claude setups for any project
Project-URL: Homepage, https://github.com/claude-setup/claude-setup
Project-URL: Documentation, https://docs.claude-setup.dev
Project-URL: Repository, https://github.com/claude-setup/claude-setup.git
Project-URL: Issues, https://github.com/claude-setup/claude-setup/issues
Project-URL: Changelog, https://github.com/claude-setup/claude-setup/blob/main/CHANGELOG.md
Author-email: Claude Setup Contributors <hello@claude-setup.dev>
Maintainer-email: Claude Setup Maintainers <hello@claude-setup.dev>
License: MIT
License-File: LICENSE
Keywords: ai,automation,claude,claude-code,cli,configuration,developer-experience,development-tools,llm,scaffolding
Classifier: Development Status :: 5 - Production/Stable
Classifier: Environment :: Console
Classifier: Intended Audience :: Developers
Classifier: License :: OSI Approved :: MIT License
Classifier: Operating System :: OS Independent
Classifier: Programming Language :: Python :: 3
Classifier: Programming Language :: Python :: 3.9
Classifier: Programming Language :: Python :: 3.10
Classifier: Programming Language :: Python :: 3.11
Classifier: Programming Language :: Python :: 3.12
Classifier: Programming Language :: Python :: 3.13
Classifier: Topic :: Software Development :: Code Generators
Classifier: Topic :: Software Development :: Libraries :: Python Modules
Classifier: Topic :: System :: Software Distribution
Classifier: Topic :: Utilities
Classifier: Typing :: Typed
Requires-Python: >=3.9
Requires-Dist: click>=8.1.7
Requires-Dist: gitpython>=3.1.43
Requires-Dist: httpx>=0.27.0
Requires-Dist: jinja2>=3.1.4
Requires-Dist: pydantic>=2.8.0
Requires-Dist: pyyaml>=6.0.2
Requires-Dist: questionary>=2.0.1
Requires-Dist: rich>=13.7.1
Requires-Dist: toml>=0.10.2
Requires-Dist: typing-extensions>=4.12.0; python_version < '3.11'
Provides-Extra: dev
Requires-Dist: mypy>=1.11.0; extra == 'dev'
Requires-Dist: pytest-asyncio>=0.23.0; extra == 'dev'
Requires-Dist: pytest-cov>=5.0.0; extra == 'dev'
Requires-Dist: pytest>=8.3.0; extra == 'dev'
Requires-Dist: ruff>=0.6.0; extra == 'dev'
Requires-Dist: types-click; extra == 'dev'
Requires-Dist: types-pyyaml>=6.0.12; extra == 'dev'
Requires-Dist: types-toml>=0.10.8; extra == 'dev'
Provides-Extra: docs
Requires-Dist: mkdocs-material>=9.5.0; extra == 'docs'
Requires-Dist: mkdocs>=1.6.0; extra == 'docs'
Requires-Dist: mkdocstrings[python]>=0.25.0; extra == 'docs'
